persia_core.cpython-37m-x86_64-linux-gnu.so
persia_cuda111-0.1.dev251.dist-info/entry_points.txt
persia_cuda111-0.1.dev251.dist-info/WHEEL
persia_cuda111-0.1.dev251.dist-info/METADATA
persia_cuda111-0.1.dev251.dist-info/LICENSE
persia_cuda111-0.1.dev251.dist-info/top_level.txt
persia_cuda111-0.1.dev251.dist-info/RECORD
persia/version.py
persia/utils.py
persia/operator
persia/__init__.py
persia/e2e_test
persia/persia-embedding-parameter-server
persia/persia-embedding-worker
persia/prelude.py
persia/data.py
persia/helper.py
persia/launcher.py
persia/k8s_utils.py
persia/ctx.py
persia/service.py
persia/logger.py
persia/distributed.py
persia/gencrd
persia/env.py
persia/embedding/__init__.py
persia/embedding/data.py
persia/embedding/optim.py
persia_cuda111.libs/libcudart-80664282.so.10.2.89
test/utils.py
test/__init__.py
test/test_env.py
test/test_ctx.py
test/test_service.py
